flet_localisation/__init__.py
flet_localisation-0.14.0.dist-info/LICENSE
flet_localisation-0.14.0.dist-info/METADATA
flet_localisation-0.14.0.dist-info/WHEEL
flet_localisation-0.14.0.dist-info/RECORD
