Metadata-Version: 2.3
Name: flet-localisation
Version: 0.14.0
Summary: A library for a basic check of your localisation settings.
License: MIT License
Author: tct123
Author-email: 42028373+tct123@users.noreply.github.com
Requires-Python: >=3.10
Classifier: License :: Other/Proprietary License
Classifier: Programming Language :: Python :: 3
Classifier: Programming Language :: Python :: 3.10
Classifier: Programming Language :: Python :: 3.11
Classifier: Programming Language :: Python :: 3.12
Classifier: Programming Language :: Python :: 3.13
Project-URL: Bug Tracker, https://github.com/Creative-Media-Group/flet_localisation/issues
Project-URL: Repository, https://github.com/Creative-Media-Group/flet_localisation
